{
  "step": "chart_type_preview",
  "status": "completed",
  "progress": "生成图表类型预览...",
  "completed": true,
  "style": {
    "colors": [
      [
        190,
        195,
        210
      ],
      [
        43,
        48,
        49
      ],
      [
        116,
        94,
        55
      ],
      [
        207,
        172,
        101
      ],
      [
        126,
        138,
        136
      ]
    ],
    "bg_color": [
      239,
      240,
      244
    ]
  },
  "selected_data": "processed_data/App.json",
  "selected_pictogram": "",
  "selected_title": "",
  "extraction_templates": [
    [
      "d3-js/layered area chart/layered_area_plain_chart_01",
      [
        "x",
        "y",
        "group"
      ]
    ],
    [
      "d3-js/layered area chart/spline_layered_area_chart_01",
      [
        "x",
        "y",
        "group"
      ]
    ],
    [
      "d3-js/layered area chart/layered_area_chart_03",
      [
        "x",
        "y",
        "group"
      ]
    ],
    [
      "d3-js/vertical group bar chart/vertical_group_bar_chart_5",
      [
        "x",
        "y",
        "group"
      ]
    ],
    [
      "d3-js/vertical group bar chart/vertical_group_bar_chart_13",
      [
        "x",
        "y",
        "group"
      ]
    ],
    [
      "d3-js/group dot bar chart/horizontal_group_dot_bar_chart_0",
      [
        "x",
        "y",
        "group"
      ]
    ],
    [
      "d3-js/range chart/vertical_range_chart_01",
      [
        "x",
        "y",
        "group"
      ]
    ],
    [
      "d3-js/range chart/horizontal_range_bar_chart_01",
      [
        "x",
        "y",
        "group"
      ]
    ],
    [
      "d3-js/test/test",
      [
        "x",
        "y",
        "group"
      ]
    ],
    [
      "d3-js/vertical grouped bar chart/vertical_group_bar_chart_8",
      [
        "x",
        "y",
        "group"
      ]
    ],
    [
      "d3-js/vertical grouped bar chart/vertical_group_bar_plain_chart_04",
      [
        "x",
        "y",
        "group"
      ]
    ],
    [
      "d3-js/vertical grouped bar chart/triangle_group_bar_chart_01",
      [
        "x",
        "y",
        "group"
      ]
    ],
    [
      "d3-js/small multiples of spline area charts/small_multiple_spline_area_plain_chart_01",
      [
        "x",
        "y",
        "group"
      ]
    ],
    [
      "d3-js/small multiples of gauge chart/small_multiples_gauge_plain_chart_01",
      [
        "x",
        "y",
        "group"
      ]
    ],
    [
      "d3-js/small multiples of line graphs/small_multiples_line_graphs_plain_chart_01",
      [
        "x",
        "y",
        "group"
      ]
    ],
    [
      "d3-js/radial stacked area chart/radial_stacked_area_plain_chart_01",
      [
        "x",
        "y",
        "group"
      ]
    ],
    [
      "d3-js/radial stacked area chart/radial_stacked_area_chart_grid_01",
      [
        "x",
        "y",
        "group"
      ]
    ],
    [
      "d3-js/layered spline area chart/layered_spline_area_plain_chart_01",
      [
        "x",
        "y",
        "group"
      ]
    ],
    [
      "d3-js/spline graph/spline_graph_plain_chart_02",
      [
        "x",
        "y",
        "group"
      ]
    ],
    [
      "d3-js/spline graph/spline_graph_plain_chart_03",
      [
        "x",
        "y",
        "group"
      ]
    ],
    [
      "d3-js/spline graph/spline_graph_01",
      [
        "x",
        "y",
        "group"
      ]
    ],
    [
      "d3-js/horizontal group bar chart/horizontal_group_bar_plain_chart_02",
      [
        "x",
        "y",
        "group"
      ]
    ],
    [
      "d3-js/horizontal group bar chart/horizontal_group_bar_plain_chart_01",
      [
        "x",
        "y",
        "group"
      ]
    ],
    [
      "d3-js/horizontal group bar chart/horizontal_group_bar_chart_13",
      [
        "x",
        "y",
        "group"
      ]
    ],
    [
      "d3-js/horizontal group bar chart/horizontal_group_bar_chart_03",
      [
        "x",
        "y",
        "group"
      ]
    ],
    [
      "d3-js/horizontal group bar chart/horizontal_group_bar_chart_16",
      [
        "x",
        "y",
        "group"
      ]
    ],
    [
      "d3-js/horizontal group bar chart/horizontal_group_bar_chart_03_hand",
      [
        "x",
        "y",
        "group"
      ]
    ],
    [
      "d3-js/horizontal group bar chart/horizontal_group_bar_chart_06",
      [
        "x",
        "y",
        "group"
      ]
    ],
    [
      "d3-js/alluvial diagram/alluvial_diagram_plain_chart_01",
      [
        "x",
        "y",
        "group"
      ]
    ],
    [
      "d3-js/alluvial diagram/alluvial_diagram_01_dark",
      [
        "x",
        "y",
        "group"
      ]
    ],
    [
      "d3-js/radial grouped bar chart/radial_grouped_bar_plain_chart_02",
      [
        "x",
        "y",
        "group"
      ]
    ],
    [
      "d3-js/radial grouped bar chart/radial_grouped_bar_plain_chart_03",
      [
        "x",
        "y",
        "group"
      ]
    ],
    [
      "d3-js/radial grouped bar chart/radial_grouped_bar_plain_chart_01",
      [
        "x",
        "y",
        "group"
      ]
    ],
    [
      "d3-js/radial bar chart/radial_bar_chart_02",
      [
        "x",
        "y",
        "group"
      ]
    ],
    [
      "d3-js/multiple radar spline chart/multiple_radar_spline_chart_03",
      [
        "x",
        "y",
        "group"
      ]
    ],
    [
      "d3-js/multiple radar spline chart/multiple_radar_spline_chart_02",
      [
        "x",
        "y",
        "group"
      ]
    ],
    [
      "d3-js/multiple radar spline chart/multiple_radar_spline_chart_01",
      [
        "x",
        "y",
        "group"
      ]
    ],
    [
      "d3-js/multiple radar chart/multiple_radar_chart_01",
      [
        "x",
        "y",
        "group"
      ]
    ],
    [
      "d3-js/multiple radar chart/multiple_radar_chart_03",
      [
        "x",
        "y",
        "group"
      ]
    ],
    [
      "d3-js/multiple radar line chart/multiple_radar_line_chart_03",
      [
        "x",
        "y",
        "group"
      ]
    ],
    [
      "d3-js/radial range area chart/radial_range_area_chart_grid_01",
      [
        "x",
        "y",
        "group"
      ]
    ],
    [
      "d3-js/radial range area chart/radial_range_area_plain_chart_01",
      [
        "x",
        "y",
        "group"
      ]
    ],
    [
      "d3-js/radial layered spline area chart/radial_layered_spline_area_plain_chart_01",
      [
        "x",
        "y",
        "group"
      ]
    ],
    [
      "d3-js/radial layered spline area chart/radial_layered_spline_area_chart_grid_01",
      [
        "x",
        "y",
        "group"
      ]
    ],
    [
      "d3-js/horizontal diverging bar chart/horizontal_diverging_bar_chart_11",
      [
        "x",
        "y",
        "group"
      ]
    ],
    [
      "d3-js/horizontal diverging bar chart/horizontal_diverging_bar_chart_12",
      [
        "x",
        "y",
        "group"
      ]
    ],
    [
      "d3-js/horizontal diverging bar chart/horizontal_diverging_bar_chart_05",
      [
        "x",
        "y",
        "group"
      ]
    ],
    [
      "d3-js/horizontal diverging bar chart/horizontal_diverging_bar_chart_07",
      [
        "x",
        "y",
        "group"
      ]
    ],
    [
      "d3-js/diverging bar chart/diverging_bar_plain_chart_04",
      [
        "x",
        "y",
        "group"
      ]
    ],
    [
      "d3-js/diverging bar chart/diverging_bar_plain_chart_06",
      [
        "x",
        "y",
        "group"
      ]
    ],
    [
      "d3-js/diverging bar chart/diverging_bar_plain_chart_05",
      [
        "x",
        "y",
        "group"
      ]
    ],
    [
      "d3-js/multiple pie chart/multiple_pie_chart_02",
      [
        "x",
        "y",
        "group"
      ]
    ],
    [
      "d3-js/multiple pie chart/multiple_pie_chart_05",
      [
        "x",
        "y",
        "group"
      ]
    ],
    [
      "d3-js/multiple pie chart/multiple_pie_chart_03",
      [
        "x",
        "y",
        "group"
      ]
    ],
    [
      "d3-js/multiple pie chart/multiple_pie_chart_04",
      [
        "x",
        "y",
        "group"
      ]
    ],
    [
      "d3-js/diverging spline area chart/diverging_spline_area_plain_chart_01",
      [
        "x",
        "y",
        "group"
      ]
    ],
    [
      "d3-js/slope chart/slope_chart_plain_chart_01",
      [
        "x",
        "y",
        "group"
      ]
    ],
    [
      "d3-js/slope chart/slope_chart_02",
      [
        "x",
        "y",
        "group"
      ]
    ],
    [
      "d3-js/slope chart/slope_chart_01",
      [
        "x",
        "y",
        "group"
      ]
    ],
    [
      "d3-js/small multiples of area charts/small_multiple_area_plain_chart_01",
      [
        "x",
        "y",
        "group"
      ]
    ],
    [
      "d3-js/small multiples of pie charts/small_multiples_semicircle_pie_plain_chart_01",
      [
        "x",
        "y",
        "group"
      ]
    ],
    [
      "d3-js/small multiple stepped line graph/small_multiple_step_line_graph_plain_chart_01",
      [
        "x",
        "y",
        "group"
      ]
    ],
    [
      "d3-js/small multiple step line graph/small_multiple_step_line_graph_icons_01",
      [
        "x",
        "y",
        "group"
      ]
    ],
    [
      "d3-js/multiple spline graph/multiple_spline_graph_01",
      [
        "x",
        "y",
        "group"
      ]
    ],
    [
      "d3-js/multiple spline graph/multiple_spline_graph_02",
      [
        "x",
        "y",
        "group"
      ]
    ],
    [
      "d3-js/multiple line graph/multiple_line_graph_10",
      [
        "x",
        "y",
        "group"
      ]
    ],
    [
      "d3-js/multiple line graph/multiple_line_graph_12",
      [
        "x",
        "y",
        "group"
      ]
    ],
    [
      "d3-js/multiple line graph/multiple_line_graph_11",
      [
        "x",
        "y",
        "group"
      ]
    ],
    [
      "d3-js/multiple line graph/multiple_line_graph_01",
      [
        "x",
        "y",
        "group"
      ]
    ],
    [
      "d3-js/multiple line graph/multiple_line_graph_07",
      [
        "x",
        "y",
        "group"
      ]
    ],
    [
      "d3-js/multiple line graph/multiple_line_graph_06",
      [
        "x",
        "y",
        "group"
      ]
    ],
    [
      "d3-js/multiple line graph/multiple_line_graph_09",
      [
        "x",
        "y",
        "group"
      ]
    ],
    [
      "d3-js/multiple line graph/multiple_line_graph_08",
      [
        "x",
        "y",
        "group"
      ]
    ],
    [
      "d3-js/multiple line graph/multiple_line_graph_03",
      [
        "x",
        "y",
        "group"
      ]
    ],
    [
      "d3-js/multiple step line graph/multiple_step_line_graph_01",
      [
        "x",
        "y",
        "group"
      ]
    ],
    [
      "d3-js/small multiple line graph/small_multiple_line_graph_01",
      [
        "x",
        "y",
        "group"
      ]
    ],
    [
      "d3-js/radial stacked bar chart/radial_stacked_bar_plain_chart_01",
      [
        "x",
        "y",
        "group"
      ]
    ],
    [
      "d3-js/small multiples of spline graphs/small_multiples_spline_graphs_plain_chart_01",
      [
        "x",
        "y",
        "group"
      ]
    ],
    [
      "d3-js/circular stacked bar chart/circular_stacked_bar_plain_chart_01",
      [
        "x",
        "y",
        "group"
      ]
    ],
    [
      "d3-js/diverging area chart/diverging_area_plain_chart_01",
      [
        "x",
        "y",
        "group"
      ]
    ],
    [
      "d3-js/stepped line graph/stepped_line_graph_plain_chart_02",
      [
        "x",
        "y",
        "group"
      ]
    ],
    [
      "d3-js/span chart/span_plain_chart_01",
      [
        "x",
        "y",
        "group"
      ]
    ],
    [
      "d3-js/span chart/span_plain_chart_02",
      [
        "x",
        "y",
        "group"
      ]
    ],
    [
      "d3-js/small multiple area chart/small_multiple_area_chart_01",
      [
        "x",
        "y",
        "group"
      ]
    ],
    [
      "d3-js/small multiple area chart/small_multiple_area_chart_02",
      [
        "x",
        "y",
        "group"
      ]
    ],
    [
      "d3-js/stacked area chart/spline_stacked_area_chart_01",
      [
        "x",
        "y",
        "group"
      ]
    ],
    [
      "d3-js/stacked area chart/stacked_area_chart_01",
      [
        "x",
        "y",
        "group"
      ]
    ],
    [
      "d3-js/stacked area chart/stacked_area_chart_02",
      [
        "x",
        "y",
        "group"
      ]
    ],
    [
      "d3-js/stacked area chart/stacked_area_plain_chart_01",
      [
        "x",
        "y",
        "group"
      ]
    ],
    [
      "d3-js/stacked area chart/stacked_area_chart_icons_01",
      [
        "x",
        "y",
        "group"
      ]
    ],
    [
      "d3-js/stacked area chart/stacked_area_plain_chart_02",
      [
        "x",
        "y",
        "group"
      ]
    ],
    [
      "d3-js/stacked area chart/stacked_area_chart_03",
      [
        "x",
        "y",
        "group"
      ]
    ],
    [
      "d3-js/multiple area chart/multiple_area_chart_01",
      [
        "x",
        "y",
        "group"
      ]
    ],
    [
      "d3-js/multiple area chart/spline_multiple_area_chart_01",
      [
        "x",
        "y",
        "group"
      ]
    ],
    [
      "d3-js/range area chart/range_area_chart_01",
      [
        "x",
        "y",
        "group"
      ]
    ],
    [
      "d3-js/range area chart/range_area_chart_icons_01",
      [
        "x",
        "y",
        "group"
      ]
    ],
    [
      "d3-js/range area chart/range_area_plain_chart_01",
      [
        "x",
        "y",
        "group"
      ]
    ],
    [
      "d3-js/dumbbell plot/dumbbell_plot_plain_chart_01",
      [
        "x",
        "y",
        "group"
      ]
    ],
    [
      "d3-js/dumbbell plot/dumbbell_plot_plain_chart_02",
      [
        "x",
        "y",
        "group"
      ]
    ],
    [
      "d3-js/line graph/line_graph_plain_chart_03",
      [
        "x",
        "y",
        "group"
      ]
    ],
    [
      "d3-js/line graph/line_graph_plain_chart_02",
      [
        "x",
        "y",
        "group"
      ]
    ],
    [
      "d3-js/line graph/line_graph_plain_chart_01",
      [
        "x",
        "y",
        "group"
      ]
    ],
    [
      "d3-js/stacked circular bar chart/stacked_circular_bar_chart_03",
      [
        "x",
        "y",
        "group"
      ]
    ],
    [
      "d3-js/group radial bar chart/group_radial_bar_chart_01",
      [
        "x",
        "y",
        "group"
      ]
    ],
    [
      "d3-js/group radial bar chart/group_radial_bar_chart_02",
      [
        "x",
        "y",
        "group"
      ]
    ],
    [
      "d3-js/group radial bar chart/group_radial_bar_chart_03",
      [
        "x",
        "y",
        "group"
      ]
    ],
    [
      "d3-js/stacked radial bar chart/stacked_radial_bar_chart_02",
      [
        "x",
        "y",
        "group"
      ]
    ],
    [
      "d3-js/stacked radial bar chart/stacked_radial_bar_chart_01",
      [
        "x",
        "y",
        "group"
      ]
    ],
    [
      "d3-js/radial layered area chart/radial_layered_area_chart_grid_01",
      [
        "x",
        "y",
        "group"
      ]
    ],
    [
      "d3-js/radial layered area chart/radial_layered_area_plain_chart_01",
      [
        "x",
        "y",
        "group"
      ]
    ]
  ],
  "id": "App",
  "chart_type_page": 0,
  "variation_page": 0,
  "selected_chart_type": "",
  "available_chart_types": [
    {
      "type": "horizontal bar chart",
      "template": "d3-js/horizontal bar chart/horizontal_bar_chart_1",
      "image_url": "/static/chart_types/Horizontal Bar Chart.png"
    },
    {
      "type": "vertical bar chart",
      "template": "d3-js/vertical bar chart/vertical_bar_chart_07_2",
      "image_url": "/static/chart_types/Vertical Bar Chart.png"
    },
    {
      "type": "proportional area chart (circle)",
      "template": "d3-js/proportional area chart (circle)/proportional_area_chart_circle_12",
      "image_url": "/static/chart_types/Proportional Area Chart.png"
    },
    {
      "type": "proportional area chart (square)",
      "template": "d3-js/proportional area chart (square)/proportional_area_chart_square_09",
      "image_url": "/static/chart_types/Proportional Area Chart.png"
    },
    {
      "type": "proportional area chart (triangle)",
      "template": "d3-js/proportional area chart (triangle)/proportional_area_chart_triangle_05",
      "image_url": "/static/chart_types/Proportional Area Chart.png"
    },
    {
      "type": "circular bar chart",
      "template": "d3-js/circular bar chart/circular_bar_chart_01",
      "image_url": "/static/chart_types/Circular Bar Chart.png"
    },
    {
      "type": "lollipop chart",
      "template": "d3-js/lollipop chart/horizontal_lollipop_chart_02",
      "image_url": "/static/chart_types/Lollipop Chart.png"
    },
    {
      "type": "radial bar chart",
      "template": "d3-js/radial bar chart/radial_bar_chart_05",
      "image_url": "/static/chart_types/Radial Bar Chart.png"
    },
    {
      "type": "horizontal dot bar chart",
      "template": "d3-js/horizontal dot bar chart/horizontal_dot_bar_chart_02",
      "image_url": "/static/chart_types/Horizontal Dot Bar Chart.png"
    },
    {
      "type": "proportional area chart (pentagram)",
      "template": "d3-js/proportional area chart (pentagram)/proportional_area_chart_pentagram_02",
      "image_url": null
    }
  ],
  "available_variations": [],
  "reference_page": 14,
  "selected_reference": "infographics/Space-Origin.png",
  "reference_descriptions": {
    "title_description": "1. **Text Layout**: The text is divided into two lines. The first line has four words, while the second line has seven words. The text is center-aligned.\n\n2. **Font Style**: The font is sans-serif, bold, and not italicized. It has a clean and modern appearance.\n\n3. **Color Scheme**: The text color is dark gray or black, creating a strong contrast against a light background, which is likely white or very light gray.\n\n4. **Decorative Effects**: There are no additional decorative effects such as shadows, outlines, or glow. The text is simple with no icons or decorative elements integrated into it.\n\n5. **Overall Style**: The overall style is modern, minimalistic, and straightforward, conveying a sense of professionalism and clarity. It has a clean and no-frills aesthetic, suitable for corporate or analytical content.",
    "pictogram_description": "1. **Content Theme**: The image depicts stacks of money in the form of dollar bills, suggesting financial or revenue-focused content, possibly related to Apple's financial performance. The main elements include bundles of hundred-dollar bills and the Apple logo.\n\n2. **Drawing Style**: The style is a semi-realistic rendering with elements of 3D visual representation, particularly noticeable in the depiction of the money stacks. The lines around the money are precise and moderately thick, providing a clear but stylized representation.\n\n3. **Color Scheme**: The colors used are mostly realistic for the money, featuring greens, grays, and yellows typical of US currency. The Apple logo background is a soft blue and gray tone, which is more subdued and complements the foreground elements without over-shadowing them. There are no gradients used.\n\n4. **Background Treatment**: The background is a large, stylized Apple logo with a soft bluish-gray color. It is a solid shape, lending a clean and corporate feel to the image without any patterns or textures.\n\n5. **Overall Characteristics**: The visual features a structured composition with a clear focal point on the money stacks. It exhibits a business-oriented style with realistic elements combined with branding, offering a professional and clean appearance."
  },
  "title_options": {
    "title_0_72947699.png": {
      "title_text": "Global Space Exploration Funding by Country",
      "image_path": "buffer/Space/title_0_72947699.png",
      "success": true
    },
    "title_1_72947699.png": {
      "title_text": "Global Space Exploration Funding by Country",
      "image_path": "buffer/Space/title_1_72947699.png",
      "success": true
    },
    "title_2_72947699.png": {
      "title_text": "Global Space Exploration Funding by Country",
      "image_path": "buffer/Space/title_2_72947699.png",
      "success": true
    }
  },
  "current_title_text": "Global Space Exploration Funding by Country",
  "pictogram_options": {
    "pictogram_0_8f6a3a3b.png": {
      "pictogram_prompt": "Cached",
      "image_path": "buffer/Space/pictogram_0_8f6a3a3b.png",
      "success": true
    },
    "pictogram_1_8f6a3a3b.png": {
      "pictogram_prompt": "Cached",
      "image_path": "buffer/Space/pictogram_1_8f6a3a3b.png",
      "success": true
    },
    "pictogram_2_8f6a3a3b.png": {
      "pictogram_prompt": "Cached",
      "image_path": "buffer/Space/pictogram_2_8f6a3a3b.png",
      "success": true
    }
  },
  "final_image_path": "buffer/Commute/edited_image.jpg",
  "chart_type_previews": {}
}